tf2onnx/__init__.py
tf2onnx/constants.py
tf2onnx/convert.py
tf2onnx/flexbuffers.py
tf2onnx/graph.py
tf2onnx/graph_builder.py
tf2onnx/graph_matcher.py
tf2onnx/handler.py
tf2onnx/keras2onnx_api.py
tf2onnx/schemas.py
tf2onnx/shape_inference.py
tf2onnx/symbolic_executor.py
tf2onnx/tf_loader.py
tf2onnx/tf_utils.py
tf2onnx/tfjs_utils.py
tf2onnx/tflite_utils.py
tf2onnx/tfonnx.py
tf2onnx/utils.py
tf2onnx/verbose_logging.py
tf2onnx/version.py
tf2onnx/custom_opsets/__init__.py
tf2onnx/custom_opsets/ms.py
tf2onnx/custom_opsets/onnx_ml.py
tf2onnx/custom_opsets/string_ops.py
tf2onnx/late_rewriters/__init__.py
tf2onnx/late_rewriters/channel_order_rewriters.py
tf2onnx/onnx_opset/__init__.py
tf2onnx/onnx_opset/common.py
tf2onnx/onnx_opset/controlflow.py
tf2onnx/onnx_opset/generator.py
tf2onnx/onnx_opset/logical.py
tf2onnx/onnx_opset/math.py
tf2onnx/onnx_opset/misc.py
tf2onnx/onnx_opset/nn.py
tf2onnx/onnx_opset/quantize.py
tf2onnx/onnx_opset/reduction.py
tf2onnx/onnx_opset/rnn.py
tf2onnx/onnx_opset/signal.py
tf2onnx/onnx_opset/tensor.py
tf2onnx/onnx_opset/traditionalml.py
tf2onnx/optimizer/__init__.py
tf2onnx/optimizer/back_to_back_optimizer.py
tf2onnx/optimizer/const_dequantize_optimizer.py
tf2onnx/optimizer/const_fold_optimizer.py
tf2onnx/optimizer/einsum_optimizer.py
tf2onnx/optimizer/global_pool_optimizer.py
tf2onnx/optimizer/identity_optimizer.py
tf2onnx/optimizer/loop_optimizer.py
tf2onnx/optimizer/merge_duplicated_nodes_optimizer.py
tf2onnx/optimizer/optimizer_base.py
tf2onnx/optimizer/q_dq_optimizer.py
tf2onnx/optimizer/reshape_optimizer.py
tf2onnx/optimizer/transpose_optimizer.py
tf2onnx/optimizer/upsample_optimizer.py
tf2onnx/rewriter/__init__.py
tf2onnx/rewriter/bigru_rewriter.py
tf2onnx/rewriter/bilstm_rewriter.py
tf2onnx/rewriter/cond_rewriter.py
tf2onnx/rewriter/conv2d_with_add_rewriter.py
tf2onnx/rewriter/conv2d_with_pad_rewriter.py
tf2onnx/rewriter/conv_dilations_rewriter.py
tf2onnx/rewriter/custom_rnn_rewriter.py
tf2onnx/rewriter/dropout_rewriter.py
tf2onnx-1.16.0.dist-info/LICENSE
tf2onnx-1.16.0.dist-info/METADATA
tf2onnx-1.16.0.dist-info/WHEEL
tf2onnx-1.16.0.dist-info/top_level.txt
tf2onnx-1.16.0.dist-info/RECORD
